README.md
README.rst
setup.cfg
setup.py
g_pyGle.egg-info/PKG-INFO
g_pyGle.egg-info/SOURCES.txt
g_pyGle.egg-info/dependency_links.txt
g_pyGle.egg-info/not-zip-safe
g_pyGle.egg-info/requires.txt
g_pyGle.egg-info/top_level.txt
pyGle/__init__.py
pyGle/errors.py
pyGle/version.py
pyGle/extractor/__init__.py
pyGle/url/__init__.py
pyGle/url/url_constants.py
pyGle/values/AvailableCountries.py
pyGle/values/AvailableLanguages.py
pyGle/values/InterfaceLanguages.py
pyGle/values/OptionsForPatents.py
pyGle/values/OptionsForPictures.py
pyGle/values/__init__.py