Metadata-Version: 2.1
Name: g-pyGle
Version: 1.12
Summary: A tool for searching the entire web with the Google technology
Home-page: https://github.com/Javinator9889/pyGle
Author: Javinator9889
Author-email: javialonso007@hotmail.es
License: GPL-3.0
Download-URL: https://github.com/Javinator9889/pyGle/archive/master.zip
Platform: UNKNOWN
Classifier: Development Status :: 5 - Production/Stable
Classifier: Programming Language :: Python
Classifier: License :: OSI Approved :: GNU General Public License v3 (GPLv3)
Classifier: Natural Language :: English
Classifier: Programming Language :: Python :: 3
Classifier: Programming Language :: Python :: 3.1
Classifier: Programming Language :: Python :: 3.2
Classifier: Programming Language :: Python :: 3.3
Classifier: Programming Language :: Python :: 3.4
Classifier: Programming Language :: Python :: 3.5
Classifier: Programming Language :: Python :: 3.6
Classifier: Programming Language :: Python :: 3.7
